mltaskfusion/__init__.py
mltaskfusion/cli.py
mltaskfusion/cmd/__init__.py
mltaskfusion/cmd/cli.py
mltaskfusion/db/__init__.py
mltaskfusion/db/base.py
mltaskfusion/db/redis_db.py
mltaskfusion/task/__init__.py
mltaskfusion/task/base.py
mltaskfusion/task/ollama.py
mltaskfusion/task/stablediffusion.py
mltaskfusion/task/vllm.py
mltaskfusion/utils/__init__.py
mltaskfusion/utils/config.py
mltaskfusion/utils/helper.py
mltaskfusion/utils/image.py
mltaskfusion-0.1.8.dist-info/LICENSE.txt
mltaskfusion-0.1.8.dist-info/METADATA
mltaskfusion-0.1.8.dist-info/WHEEL
mltaskfusion-0.1.8.dist-info/entry_points.txt
mltaskfusion-0.1.8.dist-info/top_level.txt
mltaskfusion-0.1.8.dist-info/RECORD
